Subdomain/Subdomainer.py
Subdomain/__init__.py
vfsrcetest-1.1.dist-info/LICENSE.txt
vfsrcetest-1.1.dist-info/METADATA
vfsrcetest-1.1.dist-info/WHEEL
vfsrcetest-1.1.dist-info/top_level.txt
vfsrcetest-1.1.dist-info/RECORD
