Metadata-Version: 2.1
Name: vfsrcetest
Version: 1.1
Summary: This use to find out all the subdomains for existing host
Author: UKVFS
License: MIT
License-File: LICENSE.txt
